{
	"classes": [
		{
			"name": "buttonRed",
			"content": "self {\n\tborder-radius: 4px;\n\tborder: 1px solid #dd3c4c;\n\tcolor: #dd3c4c;\n\tbackground-color: #FFFFFF;\n\tpadding: 10px;\n\tfont-weight: 600;\n}\n\nself {\n  transition-duration: 0.4s;\n}\n\nself:hover {\n  border: 1px solid #c32232;\n  background-color: #c32232;\n  color: #FFFFFF;\n}\n\n@media (prefers-color-scheme: dark) {\n  self {\n\tborder-radius: 4px;\n\tborder: 1px solid #ff5252;\n\tcolor: #ff5252;\n\tbackground-color: #1e1e1e; \n\tpadding: 10px;\n\tfont-weight: 600;\n  }\n  \n  self {\n\ttransition-duration: 0.4s;\n  }\n  \n  self:hover {\n\tborder: 1px solid #ff2e2e;\n\tbackground-color: #ff2e2e;\n\tcolor: #1e1e1e;\n  }\n}",
			"parentId": null,
			"id": "-t06Ra1r0hdDUV4v8RjyT"
		},
		{
			"name": "buttonBlack",
			"content": "self {\n\tborder-radius: 4px;\n\tborder: 1px solid #212529;\n\tbackground-color: #212529;\n\tcolor: #FFFFFF;\n}\n\nself {\n  transition-duration: 0.4s;\n}\n\nself:hover {\n  border: 1px solid #0b0d0e;\n  background-color: #0b0d0e;\n  color: #FFFFFF;\n}\n\n@media (prefers-color-scheme: dark) {\n  self {\n    border-radius: 4px;\n    border: 1px solid #212529;\n    background-color: #212529;\n    color: #FFFFFF;\n  }\n  \n  self {\n    transition-duration: 0.4s;\n  }\n  \n  self:hover {\n    border: 1px solid #0b0d0e;\n    background-color: #0b0d0e;\n    color: #FFFFFF;\n  }\n}",
			"parentId": null,
			"id": "VGZsvThawf_hU2xm4q45X"
		},
		{
			"name": "backgroundLoginLeft",
			"content": "self {\n    background-color: #dd3c4c;\n    color: #ffffff;\n    border-radius: 10px 0 0 10px;\n    width: 50%;\n    height: 100%;\n}\n\n@media screen and (max-width: 800px) {\n    self {\n      width: 100%;\n      height: fit-content;\n      padding-top: 40px;\n      padding-bottom: 40px;\n\n      border-radius: 10px 10px 0 0;\n    }\n  }\n\n@media (prefers-color-scheme: dark) {\n    self {\n        background-color: #c32232;\n        color: #ffffff;\n        border-radius: 10px 0 0 10px;\n      }\n\n      @media screen and (max-width: 800px) {\n        self {\n          width: 100%;\n          height: fit-content;\n       padding-top: 40px;\n       padding-bottom: 40px;\n          border-radius: 10px 10px 0 0;\n        }\n      }\n}",
			"parentId": null,
			"id": "umNirmsABdmhp5eCja7X8"
		},
		{
			"name": "label",
			"content": "self {\n   color: #717275;\n   background-color: transparent;\n}\n\nself.disabled {\n\topacity: 1;\n}\n\n@media (prefers-color-scheme: dark) {\n\tself {\n\t\tcolor: #c0c0c0;\n\t\tbackground-color: transparent;\n\t\t\n\t}\n\n\tself.disabled {\n\t\topacity: 0.5;\n\t}\n}",
			"parentId": null,
			"id": "QksB3_uGA9xyqrWMTnS6k"
		},
		{
			"name": "input",
			"content": "self {\n\tborder: 1px solid #ced4da;\n\tpadding-right : 6px;\n\tpadding-bottom : 6px;\n\tpadding-top : 6px;\n\tpadding-left : 6px;\n\tcolor: #000000;\n}\n\nself.disabled {\n\topacity: 0.9 !important;\n\tcolor: #000000;\n}\n\n@media (prefers-color-scheme: dark) {\n\tself {\n\t\tborder: 1px solid #717275; \n\t\tpadding-right: 6px;\n\t\tpadding-bottom: 6px;\n\t\tpadding-top: 6px;\n\t\tpadding-left: 6px;\n\t\tbackground-color: #0C0E12;\n\t\tcolor: #c0c0c0;\n\t}\n\n\tself.disabled {\n\t\topacity: 0.9 !important;\n\t\tcolor: #c0c0c0;\n\t}\n}",
			"parentId": null,
			"id": "PMO_yDiBMrP0HKYvIFDJb"
		},
		{
			"name": "title",
			"content": "self {\n   font-size: xx-large;\n}\n\n@media (prefers-color-scheme: dark) {\n\tself {\n      font-size: xx-large;\n      color: #e1e1e1; /* Texte clair */\n    }\n}",
			"parentId": null,
			"id": "OoXaJgMqGstknauQThs-K"
		},
		{
			"name": "DataTable",
			"content": "self {\n  border-collapse: collapse;\n}\n\nself .header{\n    height: fit-content !important;\n    border-width: 0px;\n}\n\nself .header .header-cell{\n    font-size: 18px;\n    background-color: #4f5963;\n    color:  #FFFFFF;\n    border-color: #aaadaf;\n    border-width: 0 0.5px 0 0.5px;\n}\n\nself .header .header-cell .headerTruncatedText{\n    white-space: normal;\n}\n\nself .row.selected {\n  background-color: #f3bec3;\n}\n\nself .row-even:not(.selected):not(:hover) {\n  background-color: #f8f8f8;\n}\n\n@media (prefers-color-scheme: dark) {\n  self {\n        border-collapse: collapse;\n        color: #e0e0e0;\n    }\n\n    self .header {\n        height: fit-content !important;\n        border-width: 0px;\n    }\n\n    self .header .header-cell {\n        font-size: 18px;\n        background-color: #212121;\n        color: #e0e0e0;\n        border-color: #444;\n        border-width: 0 0.5px 0 0.5px;\n    }\n\n    self .header .header-cell .headerTruncatedText {\n        white-space: normal;\n    }\n\n    self .row.selected {\n        background-color: #ff6b73; \n\t\tcolor: white\n    }\n\n    self .row-even:not(.selected):not(:hover) {\n        background-color: #2C2C2C; \n    }\n}",
			"children": {},
			"parentId": null,
			"origin": "msZvlSfNvg",
			"id": "npfQuMKJl6Wx3ypKMLgVr"
		},
		{
			"name": "box-shadow",
			"content": "self {\n  box-shadow: rgba(0, 0, 0, 0.1) 0px 1px 4px 0px;\n}\n\n@media (prefers-color-scheme: dark) {\n\tself {\n    box-shadow: rgba(255, 255, 255, 0.1) 0px 1px 4px 0px;\n  }\n}",
			"children": {},
			"parentId": null,
			"origin": "cvbwVC_Juv",
			"id": "zwUeaqVuQ-uci3CyYTQL9"
		},
		{
			"name": "buttonGrey",
			"content": "self {\n\tborder-radius: 4px;\n\tborder: 1px solid #4f5963;\n\tcolor: #4f5963;\n\tbackground-color: #FFFFFF;\n\tpadding: 10px;\n\tfont-weight: 600;\n\ttransition-duration: 0.4s;\n}\n\nself:hover {\n  border: 1px solid #394047;\n  background-color: #394047;\n  color: #FFFFFF;\n}\n\n@media (prefers-color-scheme: dark) {\n\tself {\n\t\tborder-radius: 4px;\n\t\tborder: 1px solid #e0e0e0; \n\t\tcolor: #e0e0e0; \n\t\tbackground-color: #1e1e1e; \n\t\tpadding: 10px;\n\t\tfont-weight: 600;\n\t\ttransition-duration: 0.4s;\n\t}\n\n\t/* Hover */\n\tself:hover {\n\t\tborder: 1px solid #e0e0e0;\n\t\tbackground-color: #e0e0e0;\n\t\tcolor: #1e1e1e; \n\t\t\n\t}\n}",
			"parentId": null,
			"id": "ENkvv-5LP7JIePtisIzFF"
		},
		{
			"name": "qodly-progress",
			"content": "self {\n   background-color: #f3bec3;\n}\n\n@media (prefers-color-scheme: dark) {\n\tself {\n      background-color: #c32232; /* Fond sombre adapté */\n    }\n}",
			"parentId": null,
			"id": "Sd9vvO3OHzj2IqivZO096"
		},
		{
			"name": "menuBarSelected",
			"content": "self {\n\tcolor: #dd3c4c;\n\tfont-size: 18px;\n}\n\nself:hover {\n  color: #c32232;\n}\n\n@media (prefers-color-scheme: dark) {\n\tself {\n\t\tcolor: #dd3c4c; /* Couleur rouge pour le texte sélectionné */\n\t\tfont-size: 18px;\n\t  }\n\n\t  self:hover {\n\t\tcolor: #c32232; /* Rouge plus foncé au survol */\n\t  }\n\n}",
			"parentId": null,
			"id": "nJ0G_h0RXnAY4VR1RVVK_"
		},
		{
			"name": "menuBar",
			"content": "self {\n\tcolor: #4f5963;\n\tfont-size:18px;\n\tbackground-color: transparent !important;\n}\n\nself:hover {\n\tfont-size: 18px;\n\tcolor: #394047;\n}\n\n@media (prefers-color-scheme: dark) {\n  self {\n    color: #e0e0e0; \n    font-size: 18px;\n    background-color: transparent !important; \n  }\n\n  self:hover {\n    font-size: 18px;\n    color: #b3b3b3; \n  }\n}",
			"parentId": null,
			"id": "Uj9LtZrpQp_bz6xOUq6yk"
		},
		{
			"name": "buttonLogin",
			"content": "self {\n\tborder-radius: 4px;\n\tborder: 1px solid #dd3c4c;\n\tbackground-color: #dd3c4c;\n\tcolor: #FFFFFF;\n}\n\nself {\n  transition-duration: 0.4s;\n}\n\nself:hover {\n  border: 1px solid #c32232;\n  background-color: #c32232;\n  color: #FFFFFF;\n}\n\n@media (prefers-color-scheme: dark) {\n\tself {\n\t\tborder-radius: 4px;\n\t\tborder: 1px solid #c32232;\n\t\tbackground-color: #c32232;\n\t\tcolor: #FFFFFF;\n\t}\n\t\n\tself {\n\t\ttransition-duration: 0.4s;\n\t}\n\t\n\tself:hover {\n\t\tborder: 1px solid #dd3c4c;\n\t\tbackground-color: #dd3c4c;\n\t\tcolor: #FFFFFF;\n\t}\n}",
			"parentId": null,
			"id": "Md4KhKp30EbgGiU1x9y7b"
		},
		{
			"name": "selectBox",
			"content": "self {\n\tmin-width: 200px;\n\tmax-width: 400px;\n}\n\nself .fd-selectbox__toggle_button {\n\tborder: 1px solid #ced4da;\n\tborder-radius: 4px;\n}\n\nself .FdVirtualList {\n    background-color: white;\n}\n\n/*Selected item */\nself .selected > .fd-selectbox__container {\n    background-color: #f3bec3;\n    opacity: 1;\n}\n\n/*self .FdVirtualList :hover > .fd-selectbox__container{\n    background-color: blue;\n    color: white;\n    opacity: 1;\n}*/\n\nself .disabled {\n\topacity: 0.90;\n}\n\n@media (prefers-color-scheme: dark) {\n    self {\n        min-width: 200px;\n        max-width: 400px;\n\t\tborder-width: 0px !important;\n    }\n\n\tself .fd-selectbox__toggle_button {\n\t\tbackground-color: #0C0E12;\n        color: #c0c0c0;\n\t\tborder: 1px solid #717275 !important; \n\t\tborder-radius: 4px;\n\t}\n\n\tself .FdVirtualList {\n\t\tbackground-color: #0C0E12;\n\t\tcolor: #e0e0e0;\n\t}\n\n\tself .selected > .fd-selectbox__container {\n    \tbackground-color: #ff6b73;\n\t\tcolor: white;\n    \topacity: 1;\n\t}\n\n\t/*self .FdVirtualList :hover > .fd-selectbox__container{\n    \tbackground-color: blue;\n    \tcolor: white;\n    \topacity: 1;\n\t}*/\n\t\n    self .disabled {\n    \topacity: 0.9 !important;\n\t\tcolor: #c0c0c0;/\n    }\n}",
			"parentId": null,
			"id": "JNzGU5UCYXykMFWabN4W9"
		},
		{
			"name": "tabRedLine",
			"content": "self button[data-headlessui-state] {\n\tcolor: #717275;\n\tbackground-color: transparent;\n\tborder-color: transparent !important;\n\tfont-size: 16px !important;\n\tfont-weight: 400 !important;\n\tpadding: 10px 10px;\n}\n\nself button[data-headlessui-state=\"selected\"]:after {\n\tbackground-color:  #dd3c4c !important;\n}\n\nself button[data-headlessui-state=\"selected\"] {\n\tcolor:  #dd3c4c !important;\n}\n\n@media (prefers-color-scheme: dark) {\n\t\n\tself button[data-headlessui-state] {\n\t\tcolor: #c0c0c0;\n\t\tbackground-color: transparent;\n\t\tborder-color: transparent !important;\n\t\tfont-size: 16px !important;\n\t\tfont-weight: 400 !important;\n\t\tpadding: 10px 10px;\n\t}\n\n\tself button[data-headlessui-state=\"selected\"]:after {\n\t\tbackground-color:  #ff5252 !important;\n\t}\n\n\tself button[data-headlessui-state=\"selected\"] {\n\t\tcolor:  #ff5252 !important;\n\t}\n}",
			"parentId": null,
			"id": "hsMQLjJAxPhWOwDuXGN-k"
		},
		{
			"name": "dialog",
			"content": "self {\n  padding-right : 0px;\n  padding-bottom : 0px;\n  padding-top : 0px;\n  padding-left : 0px;\n}",
			"children": {
				"Dialog": "7EJelZ01Va3IPPb5qITbI",
				"close": "W_rmW4rPzEWTXKeWI1K5g"
			},
			"parentId": null,
			"origin": "PXvV0dDXg1",
			"id": "rXZbVSGWXomEyBZnG_4KG"
		},
		{
			"id": "7EJelZ01Va3IPPb5qITbI",
			"name": "dialog__Dialog",
			"content": "",
			"parentId": "rXZbVSGWXomEyBZnG_4KG"
		},
		{
			"id": "W_rmW4rPzEWTXKeWI1K5g",
			"name": "dialog__close",
			"content": "",
			"parentId": "rXZbVSGWXomEyBZnG_4KG"
		},
		{
			"name": "position",
			"content": "self {\n  height : 100VH-108px;\n}",
			"children": {},
			"parentId": null,
			"origin": "xV39DPvnOC",
			"id": "pU3O0WuhEcfmo1bUsYOwg"
		},
		{
			"name": "date-input",
			"content": "self {\n  max-width : 200px;\n  border-radius : 4px;\n  border-width : 0.5px;\n}",
			"children": {},
			"parentId": null,
			"origin": "v3jcoMb9B5",
			"id": "Z_nRoGCJiXCv5ZU9KZF6m"
		},
		{
			"name": "boxShadow2",
			"content": "self {\n  box-shadow: 5px 10px 18px #888888; \n\tborder-radius: 10px;\n  }\n  \n  @media (prefers-color-scheme: dark) {\n    self {\n      box-shadow: 5px 10px 18px #1e1e1e;\n\t\t\tborder-radius: 10px;\n    }\n\t}",
			"parentId": null,
			"id": "gjc67vUwi3n3j9R23DCYT"
		},
		{
			"name": "home",
			"content": "self {\n\tbackground-color: var(--main-bg-color)!important;\n\tcolor: var(--main-fg-color)!important;\n}",
			"parentId": null,
			"id": "Xsmlv5-BIUAM4TTGp9-jM"
		},
		{
			"name": "sidebar",
			"content": "self {\n  background-color : var(--sidebar-bg-color);\n}",
			"children": {},
			"parentId": null,
			"origin": "yQLT6nKrq3",
			"id": "9_Crmgsc1I3MmQXRCF9qE"
		},
		{
			"name": "datePcker",
			"content": "self {\n  height : 250px;\n  width : 300px;\n  border-radius : 4px;\n  padding : 8px;\n  background-color : white;\n}\n\n@media (prefers-color-scheme: dark) {\n\tself {\n    height : 250px;\n    width : 300px;\n    border-radius : 4px;\n    padding : 8px;\n    background-color : #0c0c0c;\n\t}\n}",
			"children": {},
			"parentId": null,
			"origin": "ktaFzbp1eR",
			"id": "rNJgwjwHpJY54qmIA5PVl"
		},
		{
			"name": "footer",
			"content": "self {\n  background-color: #f0f0f0;\n  color: #3c3c3c;\n  text-align: center;\n}\n\n@media (prefers-color-scheme: dark) {\n\tself {\n\t\tbackground-color: #0c0c0c;\n\t\tcolor: #c8c8c8;\n\t\ttext-align: center;\n\t}\n}",
			"parentId": null,
			"id": "PBY04x-7C_y2usKT7T-n1"
		},
		{
			"name": "date-picker",
			"content": "self {\n  height : 250px;\n  width : 300px;\n  border-radius : 4px;\n  padding : 8px;\n  background-color : white;\n}\n\nself .datePicker-title, .yearPicker-title, .datePicker-leftIcon, .datePicker-rightIcon, .yearPicker-leftIcon, .yearPicker-rightIcon  {\n\tcolor: #000000\n}\n\nself .datePicker-days, .datePicker-weekDay, .yearPicker-years {\n\tcolor: #717275;\n}\n\nself .yearPicker-selectedYear, .datePicker-selectedDay {\n\tcolor: #1A202C;\n\t/*background-color: #f3bec3;*/\n}\n\nth[style*=\"background-color: rgb(34, 139, 230)\"], td[style*=\"background-color: rgb(34, 139, 230)\"] {\n    background-color: #f3bec3 !important;\n}\n\n@media (prefers-color-scheme: dark) {\n\tself {\n\t\theight : 250px;\n\t\twidth : 300px;\n\t\tborder-radius : 4px;\n\t\tpadding : 8px;\n\t\tbackground-color : #121212;\n\t  }\n\n\tself .datePicker-title, .yearPicker-title, .datePicker-icon, .yearPicker-leftIcon, .yearPicker-rightIcon  {\n\t\tcolor: #FFFFFF\n\t}\n\t\n\tself .datePicker-days, .datePicker-weekDay, .yearPicker-years {\n\t\t  color: #e0e0e0;\n\t  }\n\t  \n\tself .yearPicker-selectedYear, .datePicker-selectedDay {\n\t\t  color: #FFFFFF;\n\t\t  /*background-color: #dd3c4c;*/\n\t  }\n\n\tth[style*=\"background-color: rgb(34, 139, 230)\"], td[style*=\"background-color: rgb(34, 139, 230)\"] {\n    \tbackground-color: #ff6b73 !important;\n\t}\n}",
			"children": {},
			"parentId": null,
			"origin": "ktaFzbp1eR",
			"id": "qmv9yhoudF43zuUkwWgwA"
		},
		{
			"name": "constant-color",
			"content": ":root {\n\t--main-bg-color: #FFFFFF;\n\t--main-fg-color: #000000;\n\t--sidebar-bg-color: #f5f5f5;\n\n\t--accent-color1: #dd3c4c; \n\t--accent-color2: #c32232;\n\n\t--text-color1: #ffffff;\n\n\t@media (prefers-color-scheme: dark) {\n\t\t--main-bg-color: #121212;\n\t\t--main-fg-color: #E0E0E0;\n\t\t--sidebar-bg-color: #1e1e1e;\n\n\t\t--accent-color1: #c32232; \n\t\t--accent-color2: #dd3c4c;\n\t}\n}",
			"parentId": null,
			"id": "BbpnVW2eNv6vTGu0HPJRX"
		},
		{
			"name": "hide-element",
			"content": "@media screen and (max-width: 800px) {\n\tself {\n\t\tdisplay:none;\n\t}\n}",
			"parentId": null,
			"id": "CHLcBxsIfpSzSMYIpq9UK"
		},
		{
			"name": "width-auto",
			"content": "@media screen and (max-width: 800px) {\n\tself {\n\t\twidth: auto;\n\t}\n}",
			"parentId": null,
			"id": "z8nwM5yNu_wvKIKUfhgaa"
		}
	]
}